qualityface/__init__.py
qualityface/api.py
qualityface/config.py
qualityface/models.py
qualityface/checkpoints/last.pth
qualityface-1.0.3.dist-info/LICENSE
qualityface-1.0.3.dist-info/METADATA
qualityface-1.0.3.dist-info/WHEEL
qualityface-1.0.3.dist-info/top_level.txt
qualityface-1.0.3.dist-info/RECORD
